{
  "product_name": "EV Calculator",
  "tagline": "Quantify every trade before you take it",
  "accent_color": "#6B6BF8",
  "screen_video_url": "http://localhost:4322/sessions/0438edfa-411e-4c1f-89b5-38fb2b37e8f8/screen.mp4",
  "style_seed": "0438edfa-411e-4c1f-89b5-38fb2b37e8f8",
  "scenes": [
    {
      "type": "intro",
      "duration": 120,
      "title": "EV Calculator",
      "subtitle": "Quantify every trade before you take it",
      "video_start_ms": 0
    },
    {
      "type": "interaction",
      "duration": 150,
      "video_start_ms": 34517,
      "click_ms": 35038,
      "click_x": null,
      "click_y": null,
      "scroll_before": 0,
      "callout_text": "Enter your price",
      "step_number": 1
    },
    {
      "type": "interaction",
      "duration": 150,
      "video_start_ms": 37389,
      "click_ms": 37900,
      "click_x": null,
      "click_y": null,
      "scroll_before": 0,
      "callout_text": "Set position size",
      "step_number": 2
    },
    {
      "type": "interaction",
      "duration": 150,
      "video_start_ms": 40257,
      "click_ms": 40760,
      "click_x": null,
      "click_y": null,
      "scroll_before": 0,
      "callout_text": "Define price targets",
      "step_number": 3
    },
    {
      "type": "interaction",
      "duration": 150,
      "video_start_ms": 43069,
      "click_ms": 43580,
      "click_x": null,
      "click_y": null,
      "scroll_before": 831,
      "callout_text": "Set take-profit target",
      "step_number": 4
    },
    {
      "type": "result",
      "duration": 120,
      "video_start_ms": 48915,
      "callout_text": "Instant EV result!"
    },
    {
      "type": "outro",
      "duration": 100,
      "cta": "Try EV Calculator"
    }
  ]
}